VerilogCam_project/modules/convolution_filt/convolution_filt.sv
module convolution_filt #(parameter W = 6, W_FRAC = 3) (
    input clk,
    input [2:0] filter_number,
    input [15:0] audio_pitch,   
    output logic signed [6:0] curr_kernel [24:0]
);

	 logic [2:0] locater;
	 logic signed [6:0] temp_kernel [24:0];
	 
//	 logic signed [6:0] clarity_kernels [99:0] = '{-6'sd1, -6'sd1, -6'sd1, -6'sd1, -6'sd1, //sharpen
//															  -6'sd1, -6'sd1, -6'sd1, -6'sd1, -6'sd1, 
//															  -6'sd1, -6'sd1, 6'sd25, -6'sd1, -6'sd1, 
//															  -6'sd1, -6'sd1, -6'sd1, -6'sd1, -6'sd1, 
//															  -6'sd1, -6'sd1, -6'sd1, -6'sd1, -6'sd1,
//															  
//															  6'sd0, 6'sd0, 6'sd0, 6'sd0, 6'sd0, //clear image
//															  6'sd0, 6'sd0, 6'sd0, 6'sd0, 6'sd0, 
//															  6'sd0, 6'sd0, 6'sd1, 6'sd0, 6'sd0, 
//															  6'sd0, 6'sd0, 6'sd0, 6'sd0, 6'sd0, 
//															  6'sd0, 6'sd0, 6'sd0, 6'sd0, 6'sd0,
//															  
//															  6'sd1, 6'sd1, 6'sd1, 6'sd1, 6'sd1, //slight blur
//															  6'sd1, 6'sd3, 6'sd3, 6'sd3, 6'sd1, 
//															  6'sd1, 6'sd3, 6'sd41, 6'sd3, 6'sd1, 
//															  6'sd1, 6'sd3, 6'sd3, 6'sd3, 6'sd1, 
//															  6'sd1, 6'sd1, 6'sd1, 6'sd1, 6'sd1,															  
//														 
//															  6'sd1, 6'sd4, 6'sd7, 6'sd4, 6'sd1, //significant blur
//															  6'sd4, 6'sd16, 6'sd26, 6'sd16, 6'sd4, 
//															  6'sd7, 6'sd26, 6'sd41, 6'sd26, 6'sd7, 
//															  6'sd4, 6'sd16, 6'sd26, 6'sd16, 6'sd4, 
//															  6'sd1, 6'sd4, 6'sd7, 6'sd4, 6'sd1
//															  };

//	 logic signed [6:0] sobel_kernels [99:0] = '{-6'sd2, -6'sd1, 6'sd0, 6'sd1, 6'sd2, //right sobel
//															  -6'sd4, -6'sd2, 6'sd0, 6'sd2, 6'sd4, 
//															  -6'sd8, -6'sd4, 6'sd0, 6'sd4, 6'sd8, 
//															  -6'sd4, -6'sd2, 6'sd0, 6'sd2, 6'sd4, 
//															  -6'sd2, -6'sd1, 6'sd0, 6'sd1, 6'sd2,  
//															  
//															  -6'sd2, -6'sd4, -6'sd8, -6'sd4, -6'sd2, //bottom sobel
//															  -6'sd1, -6'sd2, -6'sd4, -6'sd2, -6'sd1, 
//															  6'sd0, 6'sd0, 6'sd0, 6'sd0, 6'sd0, 
//															  6'sd1, 6'sd2, 6'sd4, 6'sd2, 6'sd1, 
//															  6'sd2, 6'sd4, 6'sd8, 6'sd4, 6'sd2,
//															  
//															  6'sd2, 6'sd1, 6'sd0, -6'sd1, -6'sd2, //left sobel
//															  6'sd4, 6'sd2, 6'sd0, -6'sd2, -6'sd4, 
//															  6'sd8, 6'sd4, 6'sd0, -6'sd4, -6'sd8, 
//															  6'sd4, 6'sd2, 6'sd0, -6'sd2, -6'sd4, 
//															  6'sd2, 6'sd1, 6'sd0, -6'sd1, -6'sd2,
//															  
//															  6'sd2, 6'sd4, 6'sd8, 6'sd4, 6'sd2, // top sobel
//															  6'sd1, 6'sd2, 6'sd4, 6'sd2, 6'sd1,
//															  6'sd0, 6'sd0, 6'sd0, 6'sd0, 6'sd0,
//															  -6'sd1, -6'sd2, -6'sd4, -6'sd2, -6'sd1,
//															  -6'sd2, -6'sd4, -6'sd8, -6'sd4, -6'sd2
//															  };

	 logic signed [6:0] clarity_kernels [3:0][24:0] = '{
															
															  '{7'sd0, -7'sd1, -7'sd1, -7'sd1, 7'sd0, //sharpen
															    -7'sd1, 7'sd2, 7'sd2, 7'sd2, -7'sd1, 
															    -7'sd1, 7'sd2, 7'sd8, 7'sd2, -7'sd1, 
															    -7'sd1, 7'sd2, 7'sd2, 7'sd2, -7'sd1, 
															    7'sd0, -7'sd1, -7'sd1, -7'sd1, 7'sd0},
																 
															  '{7'sd0, 7'sd0, 7'sd0, 7'sd0, 7'sd0, //clear image
															    7'sd0, 7'sd0, 7'sd0, 7'sd0, 7'sd0, 
															    7'sd0, 7'sd0, 7'sd1, 7'sd0, 7'sd0, 
															    7'sd0, 7'sd0, 7'sd0, 7'sd0, 7'sd0, 
															    7'sd0, 7'sd0, 7'sd0, 7'sd0, 7'sd0},
															   
															  '{7'sd1, 7'sd1, 7'sd1, 7'sd1, 7'sd1, //slight blur
															    7'sd1, 7'sd3, 7'sd3, 7'sd3, 7'sd1, 
															    7'sd1, 7'sd3, 7'sd41, 7'sd3, 7'sd1, 
															    7'sd1, 7'sd3, 7'sd3, 7'sd3, 7'sd1, 
															    7'sd1, 7'sd1, 7'sd1, 7'sd1, 7'sd1},															  
														   
															  '{7'sd1, 7'sd4, 7'sd7, 7'sd4, 7'sd1, //significant blur
															    7'sd4, 7'sd16, 7'sd26, 7'sd16, 7'sd4, 
															    7'sd7, 7'sd26, 7'sd41, 7'sd26, 7'sd7, 
															    7'sd4, 7'sd16, 7'sd26, 7'sd16, 7'sd4, 
															    7'sd1, 7'sd4, 7'sd7, 7'sd4, 7'sd1}
															  };
															  
															  
	 logic signed [6:0] sobel_kernels [3:0][24:0] = '{
															'{-7'sd2, -7'sd1, 7'sd0, 7'sd1, 7'sd2, //right sobel
															  -7'sd4, -7'sd2, 7'sd0, 7'sd2, 7'sd4, 
															  -7'sd8, -7'sd4, 7'sd0, 7'sd4, 7'sd8, 
															  -7'sd4, -7'sd2, 7'sd0, 7'sd2, 7'sd4, 
															  -7'sd2, -7'sd1, 7'sd0, 7'sd1, 7'sd2},  
															  
															  '{-7'sd2, -7'sd4, -7'sd8, -7'sd4, -7'sd2, //bottom sobel
															    -7'sd1, -7'sd2, -7'sd4, -7'sd2, -7'sd1, 
															     7'sd0, 7'sd0, 7'sd0, 7'sd0, 7'sd0, 
															     7'sd1, 7'sd2, 7'sd4, 7'sd2, 7'sd1, 
															     7'sd2, 7'sd4, 7'sd8, 7'sd4, 7'sd2},
															  
															  '{7'sd2, 7'sd1, 7'sd0, -7'sd1, -7'sd2, //left sobel
															    7'sd4, 7'sd2, 7'sd0, -7'sd2, -7'sd4, 
															    7'sd8, 7'sd4, 7'sd0, -7'sd4, -7'sd8, 
															    7'sd4, 7'sd2, 7'sd0, -7'sd2, -7'sd4, 
															    7'sd2, 7'sd1, 7'sd0, -7'sd1, -7'sd2},
															  
															  '{7'sd2, 7'sd4, 7'sd8, 7'sd4, 7'sd2, // top sobel
															    7'sd1, 7'sd2, 7'sd4, 7'sd2, 7'sd1,
															    7'sd0, 7'sd0, 7'sd0, 7'sd0, 7'sd0,
															   -7'sd1, -7'sd2, -7'sd4, -7'sd2, -7'sd1,
															   -7'sd2, -7'sd4, -7'sd8, -7'sd4, -7'sd2}
															  };
	 
//															  6'sd0, 6'sd0, 6'sd0, 6'sd0, 6'sd0, 
//															  6'sd0, -6'sd1, -6'sd1, -6'sd1, 6'sd0, 
//															  6'sd0, -6'sd1, 6'sd8, -6'sd1, 6'sd0, 
//															  6'sd0, -6'sd1, -6'sd1, -6'sd1, 6'sd0, 
//															  6'sd0, 6'sd0, 6'sd0, 6'sd0, 6'sd0,
															  
															  
//															  6'sd1, 6'sd1, 6'sd1, 6'sd1, 6'sd1,
//															  6'sd1, 6'sd1, 6'sd1, 6'sd1, 6'sd1, 
//															  6'sd1, 6'sd1, 6'sd1, 6'sd1, 6'sd1, 
//															  6'sd1, 6'sd1, 6'sd1, 6'sd1, 6'sd1, 
//															  6'sd1, 6'sd1, 6'sd1, 6'sd1, 6'sd1,
//															  };

    always_ff @(posedge clk) begin : determine_kernel        

		  if (filter_number < 3) begin
			   for (int i = 0; i < 25; ++i) begin
					temp_kernel[i] <= clarity_kernels[1][i];
		      end
		  end
		  else begin
			  if (audio_pitch <  65) begin
				  locater <= 0;
			  end
			  else if (audio_pitch < 130) begin
				  locater <= 1;
			  end
			  else if (audio_pitch < 199) begin
				  locater <= 2;
			  end
			  else begin
				  locater <= 3;
			  end
			  
			  if (filter_number == 3) begin
				  for (int i = 0; i < 25; ++i) begin
					  temp_kernel[i] <= clarity_kernels[locater][i];
		        end
			  end
			  else if (filter_number == 4) begin
				  for (int i = 0; i < 25; ++i) begin
					  temp_kernel[i] <= sobel_kernels[locater][i];
		        end
			  end
		  end
    end
	 
	 always_comb begin
		for (int i = 0; i < 25; i++) begin
			curr_kernel[i] = temp_kernel[i];
		end
	 end
	 
endmodule

VerilogCam_project/modules/convolution_filt/convolution_filt_tb.sv
module convolution_filt_tb;
    // Testbench Signals
    logic clk;
    logic [2:0] filter_number;
    logic [15:0] audio_pitch;
	 logic signed [6:0] expected_clarity_kernels [3:0][24:0];
	 logic signed [6:0] expected_sobel_kernels [3:0][24:0];
	 logic signed [6:0] curr_kernel [24:0];
	 logic signed [6:0] temp_kernel [24:0];
	 

    // Instantiate Module
     convolution_filt DUT (
        .clk(clk),
        .filter_number(filter_number),
        .audio_pitch(audio_pitch),
        .curr_kernel(curr_kernel)
    );
	 
	 
	 
	 initial begin
		  expected_clarity_kernels[3] = '{7'sd0, -7'sd1, -7'sd1, -7'sd1, 7'sd0, //sharpen
													 -7'sd1, 7'sd2, 7'sd2, 7'sd2, -7'sd1, 
													 -7'sd1, 7'sd2, 7'sd8, 7'sd2, -7'sd1, 
													 -7'sd1, 7'sd2, 7'sd2, 7'sd2, -7'sd1, 
													 7'sd0, -7'sd1, -7'sd1, -7'sd1, 7'sd0};
                               
		expected_clarity_kernels[2] = '{7'sd0, 7'sd0, 7'sd0, 7'sd0, 7'sd0, // expected clear image
												 7'sd0, 7'sd0, 7'sd0, 7'sd0, 7'sd0,
												 7'sd0, 7'sd0, 7'sd1, 7'sd0, 7'sd0,
												 7'sd0, 7'sd0, 7'sd0, 7'sd0, 7'sd0,
												 7'sd0, 7'sd0, 7'sd0, 7'sd0, 7'sd0};
												 
		expected_clarity_kernels[1] = '{7'sd1, 7'sd1, 7'sd1, 7'sd1, 7'sd1, // expected slight blur
												 7'sd1, 7'sd3, 7'sd3, 7'sd3, 7'sd1,
												 7'sd1, 7'sd3, 7'sd41, 7'sd3, 7'sd1,
												 7'sd1, 7'sd3, 7'sd3, 7'sd3, 7'sd1,
												 7'sd1, 7'sd1, 7'sd1, 7'sd1, 7'sd1};
												 
		expected_clarity_kernels[0] = '{7'sd1, 7'sd4, 7'sd7, 7'sd4, 7'sd1, // expected significant blur
												 7'sd4, 7'sd16, 7'sd26, 7'sd16, 7'sd4,
												 7'sd7, 7'sd26, 7'sd41, 7'sd26, 7'sd7,
												 7'sd4, 7'sd16, 7'sd26, 7'sd16, 7'sd4,
												 7'sd1, 7'sd4, 7'sd7, 7'sd4, 7'sd1};
												 
		expected_sobel_kernels[3] = '{-7'sd2, -7'sd1, 7'sd0, 7'sd1, 7'sd2,  // right sobel -2
												-7'sd4, -7'sd2, 7'sd0, 7'sd2, 7'sd4, 
												-7'sd8, -7'sd4, 7'sd0, 7'sd4, 7'sd8, 
												-7'sd4, -7'sd2, 7'sd0, 7'sd2, 7'sd4, 
												-7'sd2, -7'sd1, 7'sd0, 7'sd1, 7'sd2};
												
		expected_sobel_kernels[2] = '{-7'sd2, -7'sd4, -7'sd8, -7'sd4, -7'sd2,  // bottom sobel -2
												-7'sd1, -7'sd2, -7'sd4, -7'sd2, -7'sd1, 
												7'sd0, 7'sd0, 7'sd0, 7'sd0, 7'sd0, 
												7'sd1, 7'sd2, 7'sd4, 7'sd2, 7'sd1, 
												7'sd2, 7'sd4, 7'sd8, 7'sd4, 7'sd2};
												
		expected_sobel_kernels[1] = '{7'sd2, 7'sd1, 7'sd0, -7'sd1, -7'sd2,  // left sobel 2
												7'sd4, 7'sd2, 7'sd0, -7'sd2, -7'sd4, 
												7'sd8, 7'sd4, 7'sd0, -7'sd4, -7'sd8, 
												7'sd4, 7'sd2, 7'sd0, -7'sd2, -7'sd4, 
												7'sd2, 7'sd1, 7'sd0, -7'sd1, -7'sd2};
												
		expected_sobel_kernels[0] = '{7'sd2, 7'sd4, 7'sd8, 7'sd4, 7'sd2,  // top sobel 2
												7'sd1, 7'sd2, 7'sd4, 7'sd2, 7'sd1, 
												7'sd0, 7'sd0, 7'sd0, 7'sd0, 7'sd0, 
												-7'sd1, -7'sd2, -7'sd4, -7'sd2, -7'sd1, 
												-7'sd2, -7'sd4, -7'sd8, -7'sd4, -7'sd2};

	 end
										 
		
	 
	 
	 initial begin
		clk = 0;
		forever #5 clk = ~clk;
	 end


	initial begin
		$dumpfile("waveform.vcd");
      $dumpvars();
		
		#10;
		filter_number = 0;
		audio_pitch = 0;
		
		#10;
		
		for (int i = 0; i < 5; i++) begin
			#100
			for (int j = 0; j < 25; j++) begin
				assert(curr_kernel[j] == expected_clarity_kernels[1][j]) else $fatal("incorrect index %d, clarity 1", j);
			end
			if (i == 2) begin
				filter_number = 2;
				audio_pitch = 64;
			end
		end
		
		#10;
		
		filter_number = 3;
		
		for (int i = 0; i < 5; i++) begin
			#100
			for (int j = 0; j < 25; j++) begin
				assert(curr_kernel[j] == expected_clarity_kernels[0][j]) else $fatal("incorrect index %d, clarity 0", i);
			end
		end
		
		#10;
		
		audio_pitch = 175;
		
		for (int i = 0; i < 5; i++) begin
			#100
			for (int j = 0; j < 25; j++) begin
				assert(curr_kernel[j] == expected_clarity_kernels[2][j]) else $fatal("incorrect index %d, clarity 2", i);
			end
		end
		
		#10;
		
		filter_number = 4;
		
		for (int i = 0; i < 5; i++) begin
			#100
			for (int j = 0; j < 25; j++) begin
				assert(curr_kernel[j] == expected_sobel_kernels[2][j]) else $fatal("incorrect index %d, sobel 2", i);
			end
		end
		
		#10;
		
		filter_number = 1;
		
		for (int i = 0; i < 5; i++) begin
			#100
			for (int j = 0; j < 25; j++) begin
				assert(curr_kernel[j] == expected_clarity_kernels[1][j]) else $fatal("incorrect index %d, clarity 1", i);
			end
		end
		
		#10;
		
		filter_number = 4;
		
		for (int i = 0; i < 5; i++) begin
			#100
			for (int j = 0; j < 25; j++) begin
				assert(curr_kernel[j] == expected_sobel_kernels[2][j]) else $fatal("incorrect index %d, clarity 2", i);
			end
		end
	
		#10;
		
		filter_number = 3;
		audio_pitch = 200;
		
		for (int i = 0; i < 5; i++) begin
			#100
			for (int j = 0; j < 25; j++) begin
				assert(curr_kernel[j] == expected_clarity_kernels[3][j]) else $fatal("incorrect index %0d, clarity 3", i);
			end
		end
		
		#200
		$finish();
	end
endmodule

VerilogCam_project/modules/convolution_filt/obj_dir/waveform.vcd
$version Generated by VerilatedVcd $end
$timescale 1ps $end
 $scope module TOP $end
  $scope module convolution_filt_tb $end
   $var wire 1 c clk $end
   $var wire 3 d filter_number [2:0] $end
   $var wire 16 e audio_pitch [15:0] $end
   $var wire 7 - curr_kernel[0] [6:0] $end
   $var wire 7 . curr_kernel[1] [6:0] $end
   $var wire 7 / curr_kernel[2] [6:0] $end
   $var wire 7 0 curr_kernel[3] [6:0] $end
   $var wire 7 1 curr_kernel[4] [6:0] $end
   $var wire 7 2 curr_kernel[5] [6:0] $end
   $var wire 7 3 curr_kernel[6] [6:0] $end
   $var wire 7 4 curr_kernel[7] [6:0] $end
   $var wire 7 5 curr_kernel[8] [6:0] $end
   $var wire 7 6 curr_kernel[9] [6:0] $end
   $var wire 7 7 curr_kernel[10] [6:0] $end
   $var wire 7 8 curr_kernel[11] [6:0] $end
   $var wire 7 9 curr_kernel[12] [6:0] $end
   $var wire 7 : curr_kernel[13] [6:0] $end
   $var wire 7 ; curr_kernel[14] [6:0] $end
   $var wire 7 < curr_kernel[15] [6:0] $end
   $var wire 7 = curr_kernel[16] [6:0] $end
   $var wire 7 > curr_kernel[17] [6:0] $end
   $var wire 7 ? curr_kernel[18] [6:0] $end
   $var wire 7 @ curr_kernel[19] [6:0] $end
   $var wire 7 A curr_kernel[20] [6:0] $end
   $var wire 7 B curr_kernel[21] [6:0] $end
   $var wire 7 C curr_kernel[22] [6:0] $end
   $var wire 7 D curr_kernel[23] [6:0] $end
   $var wire 7 E curr_kernel[24] [6:0] $end
   $var wire 7 j temp_kernel[0] [6:0] $end
   $var wire 7 k temp_kernel[1] [6:0] $end
   $var wire 7 l temp_kernel[2] [6:0] $end
   $var wire 7 m temp_kernel[3] [6:0] $end
   $var wire 7 n temp_kernel[4] [6:0] $end
   $var wire 7 o temp_kernel[5] [6:0] $end
   $var wire 7 p temp_kernel[6] [6:0] $end
   $var wire 7 q temp_kernel[7] [6:0] $end
   $var wire 7 r temp_kernel[8] [6:0] $end
   $var wire 7 s temp_kernel[9] [6:0] $end
   $var wire 7 t temp_kernel[10] [6:0] $end
   $var wire 7 u temp_kernel[11] [6:0] $end
   $var wire 7 v temp_kernel[12] [6:0] $end
   $var wire 7 w temp_kernel[13] [6:0] $end
   $var wire 7 x temp_kernel[14] [6:0] $end
   $var wire 7 y temp_kernel[15] [6:0] $end
   $var wire 7 z temp_kernel[16] [6:0] $end
   $var wire 7 { temp_kernel[17] [6:0] $end
   $var wire 7 | temp_kernel[18] [6:0] $end
   $var wire 7 } temp_kernel[19] [6:0] $end
   $var wire 7 ~ temp_kernel[20] [6:0] $end
   $var wire 7 !! temp_kernel[21] [6:0] $end
   $var wire 7 "! temp_kernel[22] [6:0] $end
   $var wire 7 #! temp_kernel[23] [6:0] $end
   $var wire 7 $! temp_kernel[24] [6:0] $end
   $scope module DUT $end
    $var wire 32 %! W [31:0] $end
    $var wire 32 &! W_FRAC [31:0] $end
    $var wire 1 c clk $end
    $var wire 3 d filter_number [2:0] $end
    $var wire 16 e audio_pitch [15:0] $end
    $var wire 7 - curr_kernel[0] [6:0] $end
    $var wire 7 . curr_kernel[1] [6:0] $end
    $var wire 7 / curr_kernel[2] [6:0] $end
    $var wire 7 0 curr_kernel[3] [6:0] $end
    $var wire 7 1 curr_kernel[4] [6:0] $end
    $var wire 7 2 curr_kernel[5] [6:0] $end
    $var wire 7 3 curr_kernel[6] [6:0] $end
    $var wire 7 4 curr_kernel[7] [6:0] $end
    $var wire 7 5 curr_kernel[8] [6:0] $end
    $var wire 7 6 curr_kernel[9] [6:0] $end
    $var wire 7 7 curr_kernel[10] [6:0] $end
    $var wire 7 8 curr_kernel[11] [6:0] $end
    $var wire 7 9 curr_kernel[12] [6:0] $end
    $var wire 7 : curr_kernel[13] [6:0] $end
    $var wire 7 ; curr_kernel[14] [6:0] $end
    $var wire 7 < curr_kernel[15] [6:0] $end
    $var wire 7 = curr_kernel[16] [6:0] $end
    $var wire 7 > curr_kernel[17] [6:0] $end
    $var wire 7 ? curr_kernel[18] [6:0] $end
    $var wire 7 @ curr_kernel[19] [6:0] $end
    $var wire 7 A curr_kernel[20] [6:0] $end
    $var wire 7 B curr_kernel[21] [6:0] $end
    $var wire 7 C curr_kernel[22] [6:0] $end
    $var wire 7 D curr_kernel[23] [6:0] $end
    $var wire 7 E curr_kernel[24] [6:0] $end
    $var wire 3 F locater [2:0] $end
    $var wire 7 G temp_kernel[0] [6:0] $end
    $var wire 7 H temp_kernel[1] [6:0] $end
    $var wire 7 I temp_kernel[2] [6:0] $end
    $var wire 7 J temp_kernel[3] [6:0] $end
    $var wire 7 K temp_kernel[4] [6:0] $end
    $var wire 7 L temp_kernel[5] [6:0] $end
    $var wire 7 M temp_kernel[6] [6:0] $end
    $var wire 7 N temp_kernel[7] [6:0] $end
    $var wire 7 O temp_kernel[8] [6:0] $end
    $var wire 7 P temp_kernel[9] [6:0] $end
    $var wire 7 Q temp_kernel[10] [6:0] $end
    $var wire 7 R temp_kernel[11] [6:0] $end
    $var wire 7 S temp_kernel[12] [6:0] $end
    $var wire 7 T temp_kernel[13] [6:0] $end
    $var wire 7 U temp_kernel[14] [6:0] $end
    $var wire 7 V temp_kernel[15] [6:0] $end
    $var wire 7 W temp_kernel[16] [6:0] $end
    $var wire 7 X temp_kernel[17] [6:0] $end
    $var wire 7 Y temp_kernel[18] [6:0] $end
    $var wire 7 Z temp_kernel[19] [6:0] $end
    $var wire 7 [ temp_kernel[20] [6:0] $end
    $var wire 7 \ temp_kernel[21] [6:0] $end
    $var wire 7 ] temp_kernel[22] [6:0] $end
    $var wire 7 ^ temp_kernel[23] [6:0] $end
    $var wire 7 _ temp_kernel[24] [6:0] $end
    $scope module determine_kernel $end
     $scope module unnamedblk1 $end
      $var wire 32 ` i [31:0] $end
     $upscope $end
     $scope module unnamedblk2 $end
      $var wire 32 a i [31:0] $end
     $upscope $end
     $scope module unnamedblk3 $end
      $var wire 32 b i [31:0] $end
     $upscope $end
    $upscope $end
    $scope module unnamedblk4 $end
     $var wire 32 '! i [31:0] $end
    $upscope $end
   $upscope $end
   $scope module unnamedblk1 $end
    $var wire 32 # i [31:0] $end
    $scope module unnamedblk2 $end
     $var wire 32 $ j [31:0] $end
    $upscope $end
   $upscope $end
   $scope module unnamedblk11 $end
    $var wire 32 f i [31:0] $end
    $scope module unnamedblk12 $end
     $var wire 32 g j [31:0] $end
    $upscope $end
   $upscope $end
   $scope module unnamedblk13 $end
    $var wire 32 h i [31:0] $end
    $scope module unnamedblk14 $end
     $var wire 32 i j [31:0] $end
    $upscope $end
   $upscope $end
   $scope module unnamedblk3 $end
    $var wire 32 % i [31:0] $end
    $scope module unnamedblk4 $end
     $var wire 32 & j [31:0] $end
    $upscope $end
   $upscope $end
   $scope module unnamedblk5 $end
    $var wire 32 ' i [31:0] $end
    $scope module unnamedblk6 $end
     $var wire 32 ( j [31:0] $end
    $upscope $end
   $upscope $end
   $scope module unnamedblk7 $end
    $var wire 32 ) i [31:0] $end
    $scope module unnamedblk8 $end
     $var wire 32 * j [31:0] $end
    $upscope $end
   $upscope $end
   $scope module unnamedblk9 $end
    $var wire 32 + i [31:0] $end
    $scope module unnamedblk10 $end
     $var wire 32 , j [31:0] $end
    $upscope $end
   $upscope $end
  $upscope $end
 $upscope $end
$enddefinitions $end


#0
b00000000000000000000000000000000 #
b00000000000000000000000000000000 $
b00000000000000000000000000000000 %
b00000000000000000000000000000000 &
b00000000000000000000000000000000 '
b00000000000000000000000000000000 (
b00000000000000000000000000000000 )
b00000000000000000000000000000000 *
b00000000000000000000000000000000 +
b00000000000000000000000000000000 ,
b0000000 -
b0000000 .
b0000000 /
b0000000 0
b0000000 1
b0000000 2
b0000000 3
b0000000 4
b0000000 5
b0000000 6
b0000000 7
b0000000 8
b0000000 9
b0000000 :
b0000000 ;
b0000000 <
b0000000 =
b0000000 >
b0000000 ?
b0000000 @
b0000000 A
b0000000 B
b0000000 C
b0000000 D
b0000000 E
b000 F
b0000000 G
b0000000 H
b0000000 I
b0000000 J
b0000000 K
b0000000 L
b0000000 M
b0000000 N
b0000000 O
b0000000 P
b0000000 Q
b0000000 R
b0000000 S
b0000000 T
b0000000 U
b0000000 V
b0000000 W
b0000000 X
b0000000 Y
b0000000 Z
b0000000 [
b0000000 \
b0000000 ]
b0000000 ^
b0000000 _
b00000000000000000000000000000000 `
b00000000000000000000000000000000 a
b00000000000000000000000000000000 b
0c
b000 d
b0000000000000000 e
b00000000000000000000000000000000 f
b00000000000000000000000000000000 g
b00000000000000000000000000000000 h
b00000000000000000000000000000000 i
b0000000 j
b0000000 k
b0000000 l
b0000000 m
b0000000 n
b0000000 o
b0000000 p
b0000000 q
b0000000 r
b0000000 s
b0000000 t
b0000000 u
b0000000 v
b0000000 w
b0000000 x
b0000000 y
b0000000 z
b0000000 {
b0000000 |
b0000000 }
b0000000 ~
b0000000 !!
b0000000 "!
b0000000 #!
b0000000 $!
b00000000000000000000000000000110 %!
b00000000000000000000000000000011 &!
b00000000000000000000000000011001 '!
#5
b0000001 -
b0000001 .
b0000001 /
b0000001 0
b0000001 1
b0000001 2
b0000011 3
b0000011 4
b0000011 5
b0000001 6
b0000001 7
b0000011 8
b0101001 9
b0000011 :
b0000001 ;
b0000001 <
b0000011 =
b0000011 >
b0000011 ?
b0000001 @
b0000001 A
b0000001 B
b0000001 C
b0000001 D
b0000001 E
b0000001 G
b0000001 H
b0000001 I
b0000001 J
b0000001 K
b0000001 L
b0000011 M
b0000011 N
b0000011 O
b0000001 P
b0000001 Q
b0000011 R
b0101001 S
b0000011 T
b0000001 U
b0000001 V
b0000011 W
b0000011 X
b0000011 Y
b0000001 Z
b0000001 [
b0000001 \
b0000001 ]
b0000001 ^
b0000001 _
b00000000000000000000000000011001 `
1c
#10
0c
#15
1c
#20
0c
#25
1c
#30
0c
#35
1c
#40
0c
#45
1c
#50
0c
#55
1c
#60
0c
#65
1c
#70
0c
#75
1c
#80
0c
#85
1c
#90
0c
#95
1c
#100
0c
#105
1c
#110
0c
#115
1c
#120
b00000000000000000000000000000001 #
b00000000000000000000000000011001 $
0c
#125
1c
#130
0c
#135
1c
#140
0c
#145
1c
#150
0c
#155
1c
#160
0c
#165
1c
#170
0c
#175
1c
#180
0c
#185
1c
#190
0c
#195
1c
#200
0c
#205
1c
#210
0c
#215
1c
#220
b00000000000000000000000000000010 #
0c
#225
1c
#230
0c
#235
1c
#240
0c
#245
1c
#250
0c
#255
1c
#260
0c
#265
1c
#270
0c
#275
1c
#280
0c
#285
1c
#290
0c
#295
1c
#300
0c
#305
1c
#310
0c
#315
1c
#320
b00000000000000000000000000000011 #
0c
b010 d
b0000000001000000 e
#325
1c
#330
0c
#335
1c
#340
0c
#345
1c
#350
0c
#355
1c
#360
0c
#365
1c
#370
0c
#375
1c
#380
0c
#385
1c
#390
0c
#395
1c
#400
0c
#405
1c
#410
0c
#415
1c
#420
b00000000000000000000000000000100 #
0c
#425
1c
#430
0c
#435
1c
#440
0c
#445
1c
#450
0c
#455
1c
#460
0c
#465
1c
#470
0c
#475
1c
#480
0c
#485
1c
#490
0c
#495
1c
#500
0c
#505
1c
#510
0c
#515
1c
#520
b00000000000000000000000000000101 #
0c
#525
1c
#530
0c
b011 d
#535
b0000100 .
b0000111 /
b0000100 0
b0000100 2
b0010000 3
b0011010 4
b0010000 5
b0000100 6
b0000111 7
b0011010 8
b0011010 :
b0000111 ;
b0000100 <
b0010000 =
b0011010 >
b0010000 ?
b0000100 @
b0000100 B
b0000111 C
b0000100 D
b0000100 H
b0000111 I
b0000100 J
b0000100 L
b0010000 M
b0011010 N
b0010000 O
b0000100 P
b0000111 Q
b0011010 R
b0011010 T
b0000111 U
b0000100 V
b0010000 W
b0011010 X
b0010000 Y
b0000100 Z
b0000100 \
b0000111 ]
b0000100 ^
b00000000000000000000000000011001 a
1c
#540
0c
#545
1c
#550
0c
#555
1c
#560
0c
#565
1c
#570
0c
#575
1c
#580
0c
#585
1c
#590
0c
#595
1c
#600
0c
#605
1c
#610
0c
#615
1c
#620
0c
#625
1c
#630
b00000000000000000000000000000001 %
b00000000000000000000000000011001 &
0c
#635
1c
#640
0c
#645
1c
#650
0c
#655
1c
#660
0c
#665
1c
#670
0c
#675
1c
#680
0c
#685
1c
#690
0c
#695
1c
#700
0c
#705
1c
#710
0c
#715
1c
#720
0c
#725
1c
#730
b00000000000000000000000000000010 %
0c
#735
1c
#740
0c
#745
1c
#750
0c
#755
1c
#760
0c
#765
1c
#770
0c
#775
1c
#780
0c
#785
1c
#790
0c
#795
1c
#800
0c
#805
1c
#810
0c
#815
1c
#820
0c
#825
1c
#830
b00000000000000000000000000000011 %
0c
#835
1c
#840
0c
#845
1c
#850
0c
#855
1c
#860
0c
#865
1c
#870
0c
#875
1c
#880
0c
#885
1c
#890
0c
#895
1c
#900
0c
#905
1c
#910
0c
#915
1c
#920
0c
#925
1c
#930
b00000000000000000000000000000100 %
0c
#935
1c
#940
0c
#945
1c
#950
0c
#955
1c
#960
0c
#965
1c
#970
0c
#975
1c
#980
0c
#985
1c
#990
0c
#995
1c
#1000
0c
#1005
1c
#1010
0c
#1015
1c
#1020
0c
#1025
1c
#1030
b00000000000000000000000000000101 %
0c
#1035
1c
#1040
0c
b0000000010101111 e
#1045
b010 F
1c
#1050
0c
#1055
b0000000 -
b0000000 .
b0000000 /
b0000000 0
b0000000 1
b0000000 2
b0000000 3
b0000000 4
b0000000 5
b0000000 6
b0000000 7
b0000000 8
b0000001 9
b0000000 :
b0000000 ;
b0000000 <
b0000000 =
b0000000 >
b0000000 ?
b0000000 @
b0000000 A
b0000000 B
b0000000 C
b0000000 D
b0000000 E
b0000000 G
b0000000 H
b0000000 I
b0000000 J
b0000000 K
b0000000 L
b0000000 M
b0000000 N
b0000000 O
b0000000 P
b0000000 Q
b0000000 R
b0000001 S
b0000000 T
b0000000 U
b0000000 V
b0000000 W
b0000000 X
b0000000 Y
b0000000 Z
b0000000 [
b0000000 \
b0000000 ]
b0000000 ^
b0000000 _
1c
#1060
0c
#1065
1c
#1070
0c
#1075
1c
#1080
0c
#1085
1c
#1090
0c
#1095
1c
#1100
0c
#1105
1c
#1110
0c
#1115
1c
#1120
0c
#1125
1c
#1130
0c
#1135
1c
#1140
b00000000000000000000000000000001 '
b00000000000000000000000000011001 (
0c
#1145
1c
#1150
0c
#1155
1c
#1160
0c
#1165
1c
#1170
0c
#1175
1c
#1180
0c
#1185
1c
#1190
0c
#1195
1c
#1200
0c
#1205
1c
#1210
0c
#1215
1c
#1220
0c
#1225
1c
#1230
0c
#1235
1c
#1240
b00000000000000000000000000000010 '
0c
#1245
1c
#1250
0c
#1255
1c
#1260
0c
#1265
1c
#1270
0c
#1275
1c
#1280
0c
#1285
1c
#1290
0c
#1295
1c
#1300
0c
#1305
1c
#1310
0c
#1315
1c
#1320
0c
#1325
1c
#1330
0c
#1335
1c
#1340
b00000000000000000000000000000011 '
0c
#1345
1c
#1350
0c
#1355
1c
#1360
0c
#1365
1c
#1370
0c
