VerilogCam_project/modules/fsm/filter_fsm.sv
module filter_fsm #(
    parameter NUM_FILTERS=5
)(
    input               clk,            // 50 MHz clock
    input  logic 	    next_button,    // From debounce
    input  logic 	    prev_button,    // From debounce
    output logic [2:0]  filter_number,	// To lcd & filter modules
    output logic 	    lcd_reset		// To lcd module
); 

    // Button edge detection
    logic next_button_q, prev_button_q;
    logic next_button_edge, prev_button_edge;
	 
    always_ff @(posedge clk) begin : button_edge_detect
        next_button_q <= next_button;
        prev_button_q <= prev_button;
    end

    assign next_button_edge = next_button > next_button_q;
    assign prev_button_edge = prev_button > prev_button_q;
    assign lcd_reset = next_button_edge || prev_button_edge;

	// State Typedef Enum
    enum logic [3:0] { Filter0, Filter1, Filter2, Filter3, Filter4 } next_state, current_state = Filter0;
    
    // Next State Logic
    always_comb begin : next_state_logic
        case (current_state) /* verilator lint_off CASEINCOMPLETE */
            Filter0: next_state = next_button_edge ? Filter1 : (prev_button_edge ? Filter4 : Filter0);
            Filter1: next_state = next_button_edge ? Filter2 : (prev_button_edge ? Filter0 : Filter1);
            Filter2: next_state = next_button_edge ? Filter3 : (prev_button_edge ? Filter1 : Filter2);
            Filter3: next_state = next_button_edge ? Filter4 : (prev_button_edge ? Filter2 : Filter3);
            Filter4: next_state = next_button_edge ? Filter0 : (prev_button_edge ? Filter3 : Filter4);
            default: next_state = Filter0;
        endcase
    end
    
    // FSM State Variable Flip-Flops
    always_ff @(posedge clk) begin : fsm_ff
		current_state <= next_state;
    end

    // Continuous Output Assignments
    always_comb begin : output_assignments
		case (current_state)
            Filter0: filter_number = 3'd0;
            Filter1: filter_number = 3'd1;
            Filter2: filter_number = 3'd2;
            Filter3: filter_number = 3'd3;
            Filter4: filter_number = 3'd4;
	    endcase
    end

endmodule

VerilogCam_project/modules/fsm/filter_fsm_tb.sv
module filter_fsm_tb;

    // Parameters
    parameter NUM_FILTERS=5;

    // Testbench signals
    logic       clk;
    logic       next_button;    // From debounce
    logic       prev_button;    // From debounce
    logic [2:0] filter_number;	// To lcd display
    logic       lcd_reset;      // To lcd display

    // Instantiate device under test
    filter_fsm #(
        .NUM_FILTERS(NUM_FILTERS)
    ) dut (
        .clk(clk),
        .next_button(next_button),
        .prev_button(prev_button),
        .filter_number(filter_number),
        .lcd_reset(lcd_reset)
    );

    // Clock generation
    initial begin
        clk = 0;
        forever #5 clk = ~clk; // 100MHz clock
    end

    // Test vectors
    initial begin
        $dumpfile("a_waveform.vcd");        // File name
        $dumpvars(0, filter_select_fsm_tb); // Select all variables in the current scope
        
        // Initialize state and inputs
        next_button = 0;
        prev_button = 0; #50
		
        // Initialise to correct state (Filter1)
        assert(dut.current_state == dut.Filter0) else $fatal("Test 1 Failed: FSM initialised to incorrect state");

        // Filter1 Output Correctness
        assert(filter_number == 0) else $fatal("Test 1 Failed: Filter1 asserting incorrect filter number.");
        
        // Press next button
        next_button = 1; #10
        next_button = 0; #10

        // Test 1: Filter1 transition to Filter2 on next_button press
        assert(dut.current_state == dut.Filter1) else $fatal("Test 1 Failed: Filter1 did not transition to Filter2 on next_button press");

        // Test 2: Filter2 Output Correctness
        assert(filter_number == 1) else $fatal("Test 2 Failed: Filter2 asserting incorrect filter number.");

        // Press next button
        next_button = 1; #10
        next_button = 0; #10

        // Test 3: Filter1 transition to Filter2 on next_button press
        assert(dut.current_state == dut.Filter2) else $fatal("Test 3 Failed: Filter1 did not transition to Filter2 on next_button press");

        // Test 4: Filter2 Output Correctness
        assert(filter_number == 2) else $fatal("Test 4 Failed: Filter2 asserting incorrect filter number.");

        // Press next button
        next_button = 1; #10
        next_button = 0; #10

        // Test 5: Filter2 transition to Filter3 on next_button press
        assert(dut.current_state == dut.Filter3) else $fatal("Test 5 Failed: Filter2 did not transition to Filter3 on next_button press");

        // Test 6: Filter3 Output Correctness
        assert(filter_number == 3) else $fatal("Test 6 Failed: Filter3 asserting incorrect filter number.");

        // Press next button
        next_button = 1; #10
        next_button = 0; #10

        // Test 7: Filter3 transition to Filter4 on next_button press
        assert(dut.current_state == dut.Filter4) else $fatal("Test 7 Failed: Filter3 did not transition to Filter3 on next_button press");

        // Test 8: Filter4 Output Correctness
        assert(filter_number == 4) else $fatal("Test 8 Failed: Filter4 asserting incorrect filter number.");

        // Press next button
        next_button = 1; #10
        next_button = 0; #10

        // Test 9: Filter4 transition to Filter1 on next_button press
        assert(dut.current_state == dut.Filter0) else $fatal("Test 9 Failed: Filter4 did not transition to Filter1 on next_button press");

        // Press prev button
        prev_button = 1; #10
        prev_button = 0; #10

        // Test 10: Filter1 transition to Filter4 on prev_button press
        assert(dut.current_state == dut.Filter4) else $fatal("Test 10 Failed: Filter1 did not transition to Filter4 on prev_button press");

        // Press prev button
        prev_button = 1; #10
        prev_button = 0; #10

        // Test 11: Filter4 transition to Filter3 on prev_button press
        assert(dut.current_state == dut.Filter3) else $fatal("Test 11 Failed: Filter4 did not transition to Filter3 on prev_button press");

        // Press prev button
        prev_button = 1; #10
        prev_button = 0; #10

        // Test 12: Filter3 transition to Filter2 on prev_button press
        assert(dut.current_state == dut.Filter2) else $fatal("Test 12 Failed: Filter3 did not transition to Filter2 on prev_button press");

        // Press prev button
        prev_button = 1; #10
        prev_button = 0; #10

        // Test 13: Filter2 transition to Filter1 on prev_button press
        assert(dut.current_state == dut.Filter1) else $fatal("Test 13 Failed: Filter2 did not transition to Filter1 on prev_button press");

        // Press prev button
        prev_button = 1; #10
        prev_button = 0; #10

        // Test 13: Filter2 transition to Filter1 on prev_button press
        assert(dut.current_state == dut.Filter0) else $fatal("Test 14 Failed: Filter1 did not transition to Filter0 on prev_button press");

        // Finish simulation
        #100;
        $finish;
    end

endmodule

VerilogCam_project/modules/fsm/obj_dir/a_waveform.vcd
$version Generated by VerilatedVcd $end
$timescale 1ps $end
 $scope module TOP $end
  $scope module filter_fsm_tb $end
   $var wire 32 . NUM_FILTERS [31:0] $end
   $var wire 1 ' clk $end
   $var wire 1 ( next_button $end
   $var wire 1 ) prev_button $end
   $var wire 3 # filter_number [2:0] $end
   $var wire 1 * lcd_reset $end
   $scope module dut $end
    $var wire 32 . NUM_FILTERS [31:0] $end
    $var wire 1 ' clk $end
    $var wire 1 ( next_button $end
    $var wire 1 ) prev_button $end
    $var wire 3 # filter_number [2:0] $end
    $var wire 1 * lcd_reset $end
    $var wire 1 $ next_button_q $end
    $var wire 1 % prev_button_q $end
    $var wire 1 + next_button_edge $end
    $var wire 1 , prev_button_edge $end
    $var wire 4 - next_state [3:0] $end
    $var wire 4 & current_state [3:0] $end
   $upscope $end
  $upscope $end
 $upscope $end
$enddefinitions $end


#0
b000 #
0$
0%
b0000 &
0'
0(
0)
0*
0+
0,
b0000 -
b00000000000000000000000000000101 .
#5
1'
#10
0'
#15
1'
#20
0'
#25
1'
#30
0'
#35
1'
#40
0'
#45
1'
#50
0'
1(
1*
1+
b0001 -
#55
b001 #
1$
b0001 &
1'
0*
0+
#60
0'
0(
#65
0$
1'
#70
0'
1(
1*
1+
b0010 -
#75
b010 #
1$
b0010 &
1'
0*
0+
#80
0'
0(
#85
0$
1'
#90
0'
1(
1*
1+
b0011 -
#95
b011 #
1$
b0011 &
1'
0*
0+
#100
0'
0(
#105
0$
1'
#110
0'
1(
1*
1+
b0100 -
#115
b100 #
1$
b0100 &
1'
0*
0+
#120
0'
0(
#125
0$
1'
#130
0'
1(
1*
1+
b0000 -
#135
b000 #
1$
b0000 &
1'
0*
0+
#140
0'
0(
#145
0$
1'
#150
0'
1)
1*
1,
b0100 -
#155
b100 #
1%
b0100 &
1'
0*
0,
#160
0'
0)
#165
0%
1'
#170
0'
1)
1*
1,
b0011 -
#175
b011 #
1%
b0011 &
1'
0*
0,
#180
0'
0)
#185
0%
1'
#190
0'
1)
1*
1,
b0010 -
#195
b010 #
1%
b0010 &
1'
0*
0,
#200
0'
0)
#205
0%
1'
#210
0'
1)
1*
1,
b0001 -
#215
b001 #
1%
b0001 &
1'
0*
0,
#220
0'
0)
#225
0%
1'
#230
0'
1)
1*
1,
b0000 -
#235
b000 #
1%
b0000 &
1'
0*
0,
#240
0'
0)
#245
0%
1'
